[
	// 동로마 고유 건물
	{
		"name": "Aya Sofya",
		"uniqueTo": "Eastern Roman Empire",
		"cost": 1453,
		"happiness": 5,
		"culture": 6,
		"science": 6,
		"specialistSlots": {"Artist": 2},
		"requiredTech": "Construction",
		"uniques": ["Limited to [1] per Civilization", "[50]% production cost <upon discovering [Construction] technology>"],
		"quote": "ㅊㅋ"
		"civilopediaText": [
			{"text": "섬록암으로 만들어진 동로마제국의 랜드마크!"}
		]
	},
	{
		"name": "Storehouse",
		"replaces": "Granary",
		"uniqueTo": "Eastern Roman Empire",
		"civilopediaText": [
			{"text": "모비딕이한땀한땀정성스레만든목재창고를불태운모낙호가다시한땀한땀정성스레보수한목재창고@@@@@@@@@"}
		],
		"cost": 60,
		"food": 2,
		"production": 2,
		"maintenance": 1,
		"hurryCostModifier": 25,
		"requiredTech": "Pottery",
		"uniques": [
			"[+1 Food] from [Deer] tiles [in this city]",
			"[+1 Food] from [Bananas] tiles [in this city]",
			"[+2 Food] from [Wheat] tiles [in this city]",
			"[+2 Production] from [Stone] tiles [in this city]",
			"[+1 Production] from [Mine] tiles [in this city]",
			"Obsolete with [Agriculture] <while researching [Printing Press]>"
		]
	},
	{
		"name": "Cross",
		"replaces": "Monument",
		"uniqueTo": "Eastern Roman Empire",
		"culture": 3,
		"faith": 1,
		"cost": 40,
		"hurryCostModifier": 40,
		"maintenance": 1,
		"uniques": ["Destroyed when the city is captured"],
		"civilopediaText": [
			{"text": "블록 6개로도 만들 수 있음"}
		]
	},
	{
        "name": "Mobidick_statue",
        "uniqueTo": "Eastern Roman Empire",
        "cost": 60,
        "culture": 5,
        "production": 2,
        "science": 1,
        "requiredTech": "Bronze Working",
        "uniques": [
            "[+1 Production] from [Mine] tiles [in this city]",
            "[+2 Science] from [Marble] tiles [in this city]",
            "[1] Happiness from each type of luxury resource"
		]
	},
	{
		"name": "Alje office",
		"uniqueTo": "Eastern Roman Empire",
		"cost": 10,
		"production": 1,
		"requiredTech": "Agriculture",
		"uniques": ["[+4 Production, +2 Food] [in this city] <in cities with less than [4] [Population]>"],
		"civilopediaText": [
			{"text": "초반에는 쓸데있지만 후반에는 쓸데없음"}
		]
	},
	{
		"name": "Potato hydroponics plantation",
		"uniqueTo": "Eastern Roman Empire",
		"Food": 2,
		"Gold": 1,
		"percentStatBonus": {"food": 15},
		"cost": 80,
		"hurryCostModifier": 10,
		"maintenance": 2,
		"requiredTech": "Engineering",
		"uniques": [
			"[20]% Food is carried over after population increases [in this city]",
			"[+1 Food] from [Farm] tiles [in this city]"
			],
		"civilopediaText": [
			{"text": "3층짜리 감자농장"}
		]
	},
	{
		"name": "Enderman farm",
		"uniqueTo": "Eastern Roman Empire",
		"replaces": "Armory",
		"cost": 160,
		"hurryCostModifier": 25,
		"maintenance": 1,
		"requiredBuilding": "Barracks",
		"uniques": ["New [Military] units start with [30] XP [in this city]", "Destroyed when the city is captured"],
		"requiredTech": "Steel",
		"civilopediaText": [
			{"text": "30레벨 될 때까지 나올생각 마시오"}
		]
	},
	// 테오도시아나 고유 건물
	{
		"name": "대농장구",
		"uniqueTo": "Theodosiana Free State",
		"cost": 90,
		"hurryCostModifier": 25,
		"maintenance": 1,
		"requiredBuilding": "Granary",
		"requiredTech": "Calendar",
		"Food": 3,
		"uniques": ["Must have an owned [Grassland] within [1] tiles", "Must not be on [Hill]", "[+1 Food] from [Farm] tiles [in this city]", "[+1 Gold] from [Farm] tiles [in this city]"]
	},
	{
		"name": "크리퍼 공장",
		"uniqueTo": "Theodosiana Free State",
		"cost": 120,
		"hurryCostModifier": 50,
		"maintenance": 2,
		"requiredTech": "Engineering",
		"Production": 3,
		"uniques": [
			"[+1 Gold, +1 Production] from all [Production] buildings",
			"[+5]% Production when constructing [Melee] units [in all cities]",
			"[+10]% Production when constructing [Siege] units [in all cities]",
			"[+20]% Production when constructing [Ranged Water] units [in all cities]",
			"[+25]% Production when constructing [Gunpowder] units [in all cities]",
			"[+25]% Production when constructing [Ranged Gunpowder] units [in all cities]",
			"[+25]% Production when constructing [Guided Missile] units [in all cities]",
			"[+3] Unit Supply"
		]
	},
	{
		"name": "주민공장",
		"uniqueTo": "Theodosiana Free State",
		"cost": 95,
		"hurryCostModifier": 20,
		"maintenance": 1,
		"requiredTech": "Guilds",
		"Production": 1,
		"Food": 1,
		"Gold": 2,
		"specialistSlots": {"Merchant": 1},
		"uniques": [
			"[+2 Gold] from every [Merchant]"
		]
	},
	{
		"name": "주민 플렌테이션",
		"uniqueTo": "Theodosiana Free State",
		"cost": 120,
		"hurryCostModifier": 25,
		"maintenance": 2,
		"requiredTech": "Civil Service",
		"requiredBuilding": "주민공장",
		"Food": 1,
		"uniques": [
			"[+2 Gold, +2 Food] from every [Farm]",
			"[+2 Gold, +2 Food] from every [Plantation]",
			"[+10]% [Food] [in this city]"
		]
	},
]
